bubble_train
