Metadata-Version: 1.1
Name: bubble-train
Version: 0.0.36
Summary: Project Description
Home-page: UNKNOWN
Author: Shuo Wang <shuowang224@gmail.com>
Author-email: UNKNOWN
License: MIT
Platform: UNKNOWN
Classifier: Framework :: Dash
